pkpass_static_web_server.py
setup.py
PkpassStaticWebServer.egg-info/PKG-INFO
PkpassStaticWebServer.egg-info/SOURCES.txt
PkpassStaticWebServer.egg-info/dependency_links.txt
PkpassStaticWebServer.egg-info/entry_points.txt
PkpassStaticWebServer.egg-info/not-zip-safe
PkpassStaticWebServer.egg-info/top_level.txt