Metadata-Version: 1.0
Name: PkpassStaticWebServer
Version: 0.1.1
Summary: a static server can server pkpass file
Home-page: https://github.com/timtan/pkpass-static-web-server
Author: tim
Author-email: tim.yellow@gmail.com
License: UNKNOWN
Platform: UNKNOWN
